{
  "migrations": [
    {
      "migrationPlan": {
        "sourceProcessDefinitionKey": "Process_ApproveOrder",
        "sourceProcessVersionTag": "approveOrder_v1",
        "targetProcessDefinitionKey": "Process_ApproveOrder",
        "targetProcessVersionTag": "approveOrder_v2",
        "instructions": []
      },
      "skipIoMappings": true,
      "skipCustomListeners": true,
      "processInstanceQuery": {
        "processDefinitionKey": "Process_ApproveOrder",
        "processVersionTag": "approveOrder_v1"
      }
    }
  ]
}
